LICENSE
MANIFEST.in
README.rst
gethub.py
setup.py
bin/gethub
gethub.egg-info/PKG-INFO
gethub.egg-info/SOURCES.txt
gethub.egg-info/dependency_links.txt
gethub.egg-info/requires.txt
gethub.egg-info/top_level.txt