Metadata-Version: 1.0
Name: gethub
Version: 0.1.0
Summary: Clone all of your GitHub repositories
Home-page: http://github.com/scizzorz/gethub
Author: John Weachock
Author-email: jweachock@gmail.com
License: MIT
Platform: UNKNOWN
